etc/imgsync/imgsync.conf.sample
imgsync/__init__.py
imgsync/cmd/__init__.py
imgsync/cmd/cli.py
imgsync/commands.py
imgsync/config.py
imgsync/distros/__init__.py
imgsync/distros/base.py
imgsync/distros/debian.py
imgsync/distros/ubuntu.py
imgsync/exception.py
imgsync/glance.py
imgsync/opts.py
imgsync-2.1.0.dist-info/LICENSE
imgsync-2.1.0.dist-info/METADATA
imgsync-2.1.0.dist-info/WHEEL
imgsync-2.1.0.dist-info/entry_points.txt
imgsync-2.1.0.dist-info/RECORD
