Metadata-Version: 2.1
Name: imgsync
Version: 2.1.0
Summary: imgsync will download sync images from several distribution repositories and send them to an OpenStack Image service (Glance).
Home-page: http://github.com/alvarolopez/imgsync/
License: Apache-2.0
Author: Alvaro Lopez Garcia
Author-email: aloga@ifca.unican.es
Requires-Python: >=3.8.1,<4.0.0
Classifier: Environment :: OpenStack
Classifier: Intended Audience :: Information Technology
Classifier: Intended Audience :: System Administrators
Classifier: License :: OSI Approved :: Apache Software License
Classifier: Operating System :: POSIX :: Linux
Classifier: Programming Language :: Python
Classifier: Programming Language :: Python :: 3
Classifier: Programming Language :: Python :: 3.9
Classifier: Programming Language :: Python :: 3.10
Classifier: Programming Language :: Python :: 3.11
Classifier: Programming Language :: Python :: 3.12
Classifier: Programming Language :: Python :: 3.8
Requires-Dist: dateutils (>=0.6.12,<0.7.0)
Requires-Dist: keystoneauth1 (>=5.8.0,<6.0.0)
Requires-Dist: oslo-config (>=9.6.0,<10.0.0)
Requires-Dist: oslo-log (>=6.1.2,<7.0.0)
Requires-Dist: python-glanceclient (>=4.7.0,<5.0.0)
Requires-Dist: requests (>=2.32.3,<3.0.0)
Project-URL: Bug Tracker, http://github.com/alvarolopez/imgsync/issues
Project-URL: Repository, http://github.com/alvarolopez/imgsync/
